[
    {
        "Path":  "C:\\Users\\Asus\\Downloads\\learnwise-tamil-ai-main (1)\\majestic_pro1\\index.html",
        "LineNumber":  7
    },
    {
        "Path":  "C:\\Users\\Asus\\Downloads\\learnwise-tamil-ai-main (1)\\majestic_pro1\\index.html",
        "LineNumber":  8
    },
    {
        "Path":  "C:\\Users\\Asus\\Downloads\\learnwise-tamil-ai-main (1)\\majestic_pro1\\index.html",
        "LineNumber":  9
    },
    {
        "Path":  "C:\\Users\\Asus\\Downloads\\learnwise-tamil-ai-main (1)\\majestic_pro1\\index.html",
        "LineNumber":  12
    },
    {
        "Path":  "C:\\Users\\Asus\\Downloads\\learnwise-tamil-ai-main (1)\\majestic_pro1\\index.html",
        "LineNumber":  13
    },
    {
        "Path":  "C:\\Users\\Asus\\Downloads\\learnwise-tamil-ai-main (1)\\majestic_pro1\\index.html",
        "LineNumber":  15
    },
    {
        "Path":  "C:\\Users\\Asus\\Downloads\\learnwise-tamil-ai-main (1)\\majestic_pro1\\index.html",
        "LineNumber":  18
    },
    {
        "Path":  "C:\\Users\\Asus\\Downloads\\learnwise-tamil-ai-main (1)\\majestic_pro1\\index.html",
        "LineNumber":  19
    },
    {
        "Path":  "C:\\Users\\Asus\\Downloads\\learnwise-tamil-ai-main (1)\\majestic_pro1\\package.json",
        "LineNumber":  85
    }
]
